pydyns
