Metadata-Version: 2.1
Name: pydyns
Version: 0.0.6
Summary: A test Python bindings for DynS C++ library
Home-page: https://github.com/FishermenOnTuesdays/pydyns
Author: Karachurin Raul, Ladygin Stanislav
Author-email: karrauln@yandex.ru
License: UNKNOWN
Platform: UNKNOWN
Requires-Python: >=3.6
Provides-Extra: test
